trampolino/__init__.py
trampolino/cli.py
trampolino/trampolino.py
trampolino/utils/__init__.py
trampolino/utils/containers.py
trampolino/utils/get_example_data.py
trampolino/workflows/__init__.py
trampolino/workflows/dsi_rec.py
trampolino/workflows/dsi_trk.py
trampolino/workflows/dtk_dtirecon.py
trampolino/workflows/dtk_dtitracker.py
trampolino/workflows/dtk_spline.py
trampolino/workflows/mrtrix_msmt_csd.py
trampolino/workflows/mrtrix_tckgen.py
trampolino/workflows/mrtrix_tcksift.py
trampolino/workflows/tck2trk.py
trampolino/workflows/tractseg.py
trampolino/workflows/trekker.py
trampolino/workflows/trk2tck.py
trampolino/workflows/interfaces/__init__.py
trampolino/workflows/interfaces/diffusion_toolkit/__init__.py
trampolino/workflows/interfaces/diffusion_toolkit/base.py
trampolino/workflows/interfaces/diffusion_toolkit/dti.py
trampolino/workflows/interfaces/diffusion_toolkit/odf.py
trampolino/workflows/interfaces/diffusion_toolkit/postproc.py
trampolino/workflows/interfaces/dmri_trekker/__init__.py
trampolino/workflows/interfaces/dmri_trekker/tracking.py
trampolino/workflows/interfaces/dsi_studio/__init__.py
trampolino/workflows/interfaces/dsi_studio/rec.py
trampolino/workflows/interfaces/dsi_studio/src.py
trampolino/workflows/interfaces/dsi_studio/trk.py
trampolino/workflows/interfaces/mrtrix3/__init__.py
trampolino/workflows/interfaces/mrtrix3/base.py
trampolino/workflows/interfaces/mrtrix3/connectivity.py
trampolino/workflows/interfaces/mrtrix3/preprocess.py
trampolino/workflows/interfaces/mrtrix3/reconst.py
trampolino/workflows/interfaces/mrtrix3/tracking.py
trampolino/workflows/interfaces/mrtrix3/utils.py
trampolino/workflows/interfaces/nibabel/__init__.py
trampolino/workflows/interfaces/nibabel/conversion.py
trampolino/workflows/interfaces/tractseg/__init__.py
trampolino/workflows/interfaces/tractseg/segment.py
trampolino-0.1.8.dist-info/AUTHORS.rst
trampolino-0.1.8.dist-info/LICENSE
trampolino-0.1.8.dist-info/METADATA
trampolino-0.1.8.dist-info/WHEEL
trampolino-0.1.8.dist-info/entry_points.txt
trampolino-0.1.8.dist-info/top_level.txt
trampolino-0.1.8.dist-info/RECORD
