Metadata-Version: 2.1
Name: trampolino
Version: 0.1.8
Summary: A meta-pipeline tool for tractography based on Nipype.
Home-page: https://github.com/matteomancini/trampolino
Author: Matteo Mancini
Author-email: ingmatteomancini@gmail.com
License: MIT license
Keywords: trampolino
Platform: UNKNOWN
Classifier: Development Status :: 2 - Pre-Alpha
Classifier: Intended Audience :: Developers
Classifier: License :: OSI Approved :: MIT License
Classifier: Natural Language :: English
Classifier: Programming Language :: Python :: 2
Classifier: Programming Language :: Python :: 2.7
Classifier: Programming Language :: Python :: 3
Classifier: Programming Language :: Python :: 3.4
Classifier: Programming Language :: Python :: 3.5
Classifier: Programming Language :: Python :: 3.6
Classifier: Programming Language :: Python :: 3.7
Requires-Dist: Click (>=6.0)
Requires-Dist: nipype (>=1.5.1)
Requires-Dist: dipy (>=1.0.0)
